[
  {
    "targetMask": "C",
    "diceNum": 0,
    "visibleInBuffUi": true,
    "visibleInFightLog": true,
    "targetId": 0,
    "effectElement": -1,
    "effectUid": 211322,
    "dispellable": 3,
    "triggers": "I",
    "spellId": 13409,
    "duration": -1,
    "random": 0,
    "effectId": 950,
    "delay": 0,
    "diceSide": 0,
    "visibleInTooltip": false,
    "rawZone": "P1",
    "forClientOnly": false,
    "value": 98,
    "order": 0,
    "group": 0
  },
  {
    "targetMask": "C",
    "diceNum": 0,
    "visibleInBuffUi": true,
    "visibleInFightLog": true,
    "targetId": 0,
    "effectElement": -1,
    "effectUid": 211323,
    "dispellable": 3,
    "triggers": "I",
    "spellId": 13409,
    "duration": -1,
    "random": 0,
    "effectId": 335,
    "delay": 0,
    "diceSide": 0,
    "visibleInTooltip": false,
    "rawZone": "P1",
    "forClientOnly": false,
    "value": 0,
    "order": 1,
    "group": 0
  },
  {
    "targetMask": "a,b14",
    "diceNum": 0,
    "visibleInBuffUi": false,
    "visibleInFightLog": false,
    "targetId": 0,
    "effectElement": -1,
    "effectUid": 211324,
    "dispellable": 1,
    "triggers": "I",
    "spellId": 13409,
    "duration": 0,
    "random": 0,
    "effectId": 406,
    "delay": 0,
    "diceSide": 0,
    "visibleInTooltip": false,
    "rawZone": "X1",
    "forClientOnly": false,
    "value": 13388,
    "order": 2,
    "group": 0
  },
  {
    "targetMask": "a,b14",
    "diceNum": 0,
    "visibleInBuffUi": false,
    "visibleInFightLog": false,
    "targetId": 0,
    "effectElement": -1,
    "effectUid": 211325,
    "dispellable": 1,
    "triggers": "I",
    "spellId": 13409,
    "duration": 0,
    "random": 0,
    "effectId": 406,
    "delay": 0,
    "diceSide": 0,
    "visibleInTooltip": false,
    "rawZone": "X1",
    "forClientOnly": false,
    "value": 13387,
    "order": 3,
    "group": 0
  },
  {
    "targetMask": "a,b14",
    "diceNum": 90,
    "visibleInBuffUi": true,
    "visibleInFightLog": true,
    "targetId": 0,
    "effectElement": -1,
    "effectUid": 211326,
    "dispellable": 1,
    "triggers": "D",
    "spellId": 13409,
    "duration": 3,
    "random": 0,
    "effectId": 1163,
    "delay": 0,
    "diceSide": 0,
    "visibleInTooltip": true,
    "rawZone": "X1",
    "forClientOnly": false,
    "value": 0,
    "order": 4,
    "group": 0
  },
  {
    "targetMask": "C",
    "diceNum": 13388,
    "visibleInBuffUi": true,
    "visibleInFightLog": true,
    "targetId": 0,
    "effectElement": -1,
    "effectUid": 211327,
    "dispellable": 1,
    "triggers": "I",
    "spellId": 13409,
    "duration": 0,
    "random": 0,
    "effectId": 1045,
    "delay": 0,
    "diceSide": 0,
    "visibleInTooltip": false,
    "rawZone": "P1",
    "forClientOnly": false,
    "value": 1,
    "order": 5,
    "group": 0
  },
  {
    "targetMask": "C",
    "diceNum": 13387,
    "visibleInBuffUi": true,
    "visibleInFightLog": true,
    "targetId": 0,
    "effectElement": -1,
    "effectUid": 211328,
    "dispellable": 1,
    "triggers": "I",
    "spellId": 13409,
    "duration": 0,
    "random": 0,
    "effectId": 1045,
    "delay": 0,
    "diceSide": 0,
    "visibleInTooltip": false,
    "rawZone": "P1",
    "forClientOnly": false,
    "value": 1,
    "order": 6,
    "group": 0
  },
  {
    "targetMask": "C",
    "diceNum": 0,
    "visibleInBuffUi": false,
    "visibleInFightLog": false,
    "targetId": 0,
    "effectElement": -1,
    "effectUid": 211329,
    "dispellable": 1,
    "triggers": "I",
    "spellId": 13409,
    "duration": 0,
    "random": 0,
    "effectId": 406,
    "delay": 0,
    "diceSide": 0,
    "visibleInTooltip": false,
    "rawZone": "X1",
    "forClientOnly": false,
    "value": 13388,
    "order": 7,
    "group": 0
  },
  {
    "targetMask": "C",
    "diceNum": 0,
    "visibleInBuffUi": false,
    "visibleInFightLog": false,
    "targetId": 0,
    "effectElement": -1,
    "effectUid": 211330,
    "dispellable": 1,
    "triggers": "I",
    "spellId": 13409,
    "duration": 0,
    "random": 0,
    "effectId": 406,
    "delay": 0,
    "diceSide": 0,
    "visibleInTooltip": false,
    "rawZone": "X1",
    "forClientOnly": false,
    "value": 13387,
    "order": 8,
    "group": 0
  },
  {
    "targetMask": "C",
    "diceNum": 90,
    "visibleInBuffUi": true,
    "visibleInFightLog": true,
    "targetId": 0,
    "effectElement": -1,
    "effectUid": 211331,
    "dispellable": 1,
    "triggers": "D",
    "spellId": 13409,
    "duration": 3,
    "random": 0,
    "effectId": 1163,
    "delay": 0,
    "diceSide": 0,
    "visibleInTooltip": false,
    "rawZone": "X1",
    "forClientOnly": false,
    "value": 0,
    "order": 9,
    "group": 0
  },
  {
    "targetMask": "a,b14",
    "diceNum": 0,
    "visibleInBuffUi": false,
    "visibleInFightLog": false,
    "targetId": 0,
    "effectElement": -1,
    "effectUid": 211376,
    "dispellable": 1,
    "triggers": "I",
    "spellId": 13409,
    "duration": 0,
    "random": 0,
    "effectId": 406,
    "delay": 0,
    "diceSide": 0,
    "visibleInTooltip": false,
    "rawZone": "X1",
    "forClientOnly": false,
    "value": 13414,
    "order": 10,
    "group": 0
  },
  {
    "targetMask": "a,b14",
    "diceNum": 0,
    "visibleInBuffUi": false,
    "visibleInFightLog": false,
    "targetId": 0,
    "effectElement": -1,
    "effectUid": 211377,
    "dispellable": 1,
    "triggers": "I",
    "spellId": 13409,
    "duration": 0,
    "random": 0,
    "effectId": 406,
    "delay": 0,
    "diceSide": 0,
    "visibleInTooltip": false,
    "rawZone": "X1",
    "forClientOnly": false,
    "value": 13406,
    "order": 11,
    "group": 0
  },
  {
    "targetMask": "C",
    "diceNum": 0,
    "visibleInBuffUi": false,
    "visibleInFightLog": false,
    "targetId": 0,
    "effectElement": -1,
    "effectUid": 211378,
    "dispellable": 1,
    "triggers": "I",
    "spellId": 13409,
    "duration": 0,
    "random": 0,
    "effectId": 406,
    "delay": 0,
    "diceSide": 0,
    "visibleInTooltip": false,
    "rawZone": "X1",
    "forClientOnly": false,
    "value": 13406,
    "order": 12,
    "group": 0
  },
  {
    "targetMask": "C",
    "diceNum": 0,
    "visibleInBuffUi": false,
    "visibleInFightLog": false,
    "targetId": 0,
    "effectElement": -1,
    "effectUid": 211379,
    "dispellable": 1,
    "triggers": "I",
    "spellId": 13409,
    "duration": 0,
    "random": 0,
    "effectId": 406,
    "delay": 0,
    "diceSide": 0,
    "visibleInTooltip": false,
    "rawZone": "X1",
    "forClientOnly": false,
    "value": 13414,
    "order": 13,
    "group": 0
  },
  {
    "targetMask": "C",
    "diceNum": 13414,
    "visibleInBuffUi": true,
    "visibleInFightLog": true,
    "targetId": 0,
    "effectElement": -1,
    "effectUid": 211380,
    "dispellable": 1,
    "triggers": "I",
    "spellId": 13409,
    "duration": 0,
    "random": 0,
    "effectId": 1045,
    "delay": 0,
    "diceSide": 0,
    "visibleInTooltip": false,
    "rawZone": "P1",
    "forClientOnly": false,
    "value": 1,
    "order": 14,
    "group": 0
  },
  {
    "targetMask": "C",
    "diceNum": 13406,
    "visibleInBuffUi": true,
    "visibleInFightLog": true,
    "targetId": 0,
    "effectElement": -1,
    "effectUid": 211381,
    "dispellable": 1,
    "triggers": "I",
    "spellId": 13409,
    "duration": 0,
    "random": 0,
    "effectId": 1045,
    "delay": 0,
    "diceSide": 0,
    "visibleInTooltip": false,
    "rawZone": "P1",
    "forClientOnly": false,
    "value": 1,
    "order": 15,
    "group": 0
  }
]