[
  {
    "targetMask": "a,A",
    "diceNum": 4538,
    "visibleInBuffUi": true,
    "visibleInFightLog": true,
    "targetId": 0,
    "effectElement": -1,
    "effectUid": 123491,
    "dispellable": 1,
    "triggers": "I",
    "spellId": 4539,
    "duration": 1,
    "random": 0,
    "effectId": 402,
    "delay": 0,
    "diceSide": 1,
    "visibleInTooltip": true,
    "rawZone": "P1",
    "forClientOnly": false,
    "value": 501264,
    "order": 0,
    "group": 0
  },
  {
    "targetMask": "a,A",
    "diceNum": 41,
    "visibleInBuffUi": true,
    "visibleInFightLog": true,
    "targetId": 0,
    "effectElement": 4,
    "effectUid": 123492,
    "dispellable": 1,
    "triggers": "I",
    "spellId": 4539,
    "duration": 0,
    "random": 0,
    "effectId": 98,
    "delay": 0,
    "diceSide": 50,
    "visibleInTooltip": true,
    "rawZone": "P1",
    "forClientOnly": false,
    "value": 0,
    "order": 1,
    "group": 0
  },
  {
    "targetMask": "a,A",
    "diceNum": 3,
    "visibleInBuffUi": true,
    "visibleInFightLog": true,
    "targetId": 0,
    "effectElement": -1,
    "effectUid": 123493,
    "dispellable": 1,
    "triggers": "I",
    "spellId": 4539,
    "duration": 0,
    "random": 0,
    "effectId": 5,
    "delay": 0,
    "diceSide": 0,
    "visibleInTooltip": true,
    "rawZone": "P1",
    "forClientOnly": false,
    "value": 0,
    "order": 2,
    "group": 0
  }
]