[
  {
    "targetMask": "A",
    "diceNum": 0,
    "visibleInBuffUi": true,
    "visibleInFightLog": true,
    "targetId": 0,
    "effectElement": -1,
    "effectUid": 95457,
    "dispellable": 1,
    "triggers": "I",
    "spellId": 2416,
    "duration": 0,
    "random": 0,
    "effectId": 406,
    "delay": 0,
    "diceSide": 0,
    "visibleInTooltip": true,
    "rawZone": "P1",
    "forClientOnly": false,
    "value": 440,
    "order": 0,
    "group": 0
  },
  {
    "targetMask": "A",
    "diceNum": 71,
    "visibleInBuffUi": true,
    "visibleInFightLog": true,
    "targetId": 0,
    "effectElement": 3,
    "effectUid": 87930,
    "dispellable": 1,
    "triggers": "I",
    "spellId": 2416,
    "duration": 0,
    "random": 0,
    "effectId": 91,
    "delay": 0,
    "diceSide": 105,
    "visibleInTooltip": true,
    "rawZone": "L3",
    "forClientOnly": false,
    "value": 0,
    "order": 2,
    "group": 0
  },
  {
    "targetMask": "A",
    "diceNum": 2,
    "visibleInBuffUi": true,
    "visibleInFightLog": true,
    "targetId": 0,
    "effectElement": -1,
    "effectUid": 93250,
    "dispellable": 1,
    "triggers": "I",
    "spellId": 2416,
    "duration": 1,
    "random": 0,
    "effectId": 1080,
    "delay": 0,
    "diceSide": 3,
    "visibleInTooltip": true,
    "rawZone": "P1",
    "forClientOnly": false,
    "value": 0,
    "order": 4,
    "group": 0
  },
  {
    "targetMask": "A",
    "diceNum": 0,
    "visibleInBuffUi": true,
    "visibleInFightLog": true,
    "targetId": 0,
    "effectElement": -1,
    "effectUid": 95260,
    "dispellable": 1,
    "triggers": "I",
    "spellId": 2416,
    "duration": 2,
    "random": 0,
    "effectId": 950,
    "delay": 0,
    "diceSide": 0,
    "visibleInTooltip": true,
    "rawZone": "L3",
    "forClientOnly": false,
    "value": 40,
    "order": 6,
    "group": 0
  }
]